_wowa.abi3.so
wowa.py
wowa-1.12.dist-info/LICENSE.txt
wowa-1.12.dist-info/METADATA
wowa-1.12.dist-info/WHEEL
wowa-1.12.dist-info/top_level.txt
wowa-1.12.dist-info/RECORD
