Metadata-Version: 2.1
Name: wowa
Version: 1.12
Summary: Calculate weighted OWA functions and extending bivariate means
Home-page: UNKNOWN
Author: Gleb Beliakov, Norbert Henseler
Author-email: gleb.beliakov@deakin.edu.au, norbert.henseler@deakin.edu.au
License: UNKNOWN
Platform: UNKNOWN
License-File: LICENSE.txt
Requires-Dist: cffi (>=1.0.0)
